spam_classifier/__init__.py
spam_classifier/downloader.py
spam_classifier/model.py
tests/__init__.py
tests/test_model.py
spam_classifier-0.16.dist-info/METADATA
spam_classifier-0.16.dist-info/WHEEL
spam_classifier-0.16.dist-info/top_level.txt
spam_classifier-0.16.dist-info/RECORD
